{
  "Ether": {
    "fields": {
      "dst": {
        "description": "Destination MAC address"
      },
      "src": {
        "description": "Source MAC address"
      },
      "type": {
        "description": "EtherType"
      }
    }
  },
  "IP": {
    "fields": {
      "src": {
        "description": "Source IP"
      },
      "dst": {
        "description": "Destination IP"
      }
    },
    "can_be_payload_of": [
      "Ether"
    ]
  },
  "IPv6": {
    "fields": {
      "src": {
        "description": "Source IP"
      },
      "dst": {
        "description": "Destination IP"
      }
    },
    "can_be_payload_of": [
      "Ether"
    ]
  },
  "TCP": {
    "fields": {
      "sport": {
        "description": "Source port number"
      },
      "dport": {
        "description": "Destination port number"
      }
    },
    "can_be_payload_of": [
      "IP"
    ]
  }
}